{
  "category": {
    "name": "static-site-generators",
    "display_name": "Static site generators",
    "total_guides": 10
  },
  "meta": {
    "generated_at": "2025-09-30T06:19:17.440Z",
    "api_version": "1.0"
  },
  "guides": [
    {
      "name": "eleventy",
      "title": "eleventy Installation Guide",
      "description": "eleventy is a free and open-source static site generator. Eleventy provides simpler static site generator alternative",
      "difficulty_level": "intermediate",
      "estimated_setup_time": "15-30 minutes",
      "language": null,
      "stars": 0,
      "maintenance_status": "active",
      "supported_os": [
        "rhel",
        "centos",
        "rocky",
        "almalinux",
        "debian",
        "ubuntu",
        "arch",
        "alpine",
        "opensuse",
        "sles",
        "macos",
        "freebsd",
        "windows"
      ],
      "features": [
        "multi-os-support",
        "comprehensive-documentation",
        "security-hardening",
        "performance-optimization",
        "backup-restore-procedures",
        "troubleshooting-guides"
      ],
      "tags": [
        "static-site-generators",
        "containerization",
        "observability",
        "data-storage",
        "networking",
        "security",
        "data-protection"
      ],
      "site": "https://howtomgr.github.io/static-site-generators/eleventy/",
      "api": "https://howtomgr.github.io/api/v1/static-site-generators/eleventy.json",
      "github": "https://github.com/howtomgr/eleventy"
    },
    {
      "name": "gatsby",
      "title": "gatsby Installation Guide",
      "description": "gatsby is a free and open-source React-based generator. Gatsby provides React-based framework for creating websites and apps",
      "difficulty_level": "intermediate",
      "estimated_setup_time": "15-30 minutes",
      "language": null,
      "stars": 0,
      "maintenance_status": "active",
      "supported_os": [
        "rhel",
        "centos",
        "rocky",
        "almalinux",
        "debian",
        "ubuntu",
        "arch",
        "alpine",
        "opensuse",
        "sles",
        "macos",
        "freebsd",
        "windows"
      ],
      "features": [
        "multi-os-support",
        "comprehensive-documentation",
        "security-hardening",
        "performance-optimization",
        "backup-restore-procedures",
        "troubleshooting-guides"
      ],
      "tags": [
        "static-site-generators",
        "containerization",
        "observability",
        "data-storage",
        "networking",
        "security",
        "data-protection"
      ],
      "site": "https://howtomgr.github.io/static-site-generators/gatsby/",
      "api": "https://howtomgr.github.io/api/v1/static-site-generators/gatsby.json",
      "github": "https://github.com/howtomgr/gatsby"
    },
    {
      "name": "gridsome",
      "title": "gridsome Installation Guide",
      "description": "gridsome is a free and open-source Vue.js framework. Gridsome provides Vue.js framework for building static websites",
      "difficulty_level": "intermediate",
      "estimated_setup_time": "15-30 minutes",
      "language": null,
      "stars": 0,
      "maintenance_status": "active",
      "supported_os": [
        "rhel",
        "centos",
        "rocky",
        "almalinux",
        "debian",
        "ubuntu",
        "arch",
        "alpine",
        "opensuse",
        "sles",
        "macos",
        "freebsd",
        "windows"
      ],
      "features": [
        "multi-os-support",
        "comprehensive-documentation",
        "security-hardening",
        "performance-optimization",
        "backup-restore-procedures",
        "troubleshooting-guides"
      ],
      "tags": [
        "static-site-generators",
        "containerization",
        "observability",
        "data-storage",
        "networking",
        "security",
        "data-protection"
      ],
      "site": "https://howtomgr.github.io/static-site-generators/gridsome/",
      "api": "https://howtomgr.github.io/api/v1/static-site-generators/gridsome.json",
      "github": "https://github.com/howtomgr/gridsome"
    },
    {
      "name": "hexo",
      "title": "hexo Installation Guide",
      "description": "hexo is a free and open-source blog framework. Hexo provides fast, simple, and powerful blog framework",
      "difficulty_level": "intermediate",
      "estimated_setup_time": "15-30 minutes",
      "language": null,
      "stars": 0,
      "maintenance_status": "active",
      "supported_os": [
        "rhel",
        "centos",
        "rocky",
        "almalinux",
        "debian",
        "ubuntu",
        "arch",
        "alpine",
        "opensuse",
        "sles",
        "macos",
        "freebsd",
        "windows"
      ],
      "features": [
        "multi-os-support",
        "comprehensive-documentation",
        "security-hardening",
        "performance-optimization",
        "backup-restore-procedures",
        "troubleshooting-guides"
      ],
      "tags": [
        "static-site-generators",
        "containerization",
        "observability",
        "data-storage",
        "networking",
        "security",
        "data-protection"
      ],
      "site": "https://howtomgr.github.io/static-site-generators/hexo/",
      "api": "https://howtomgr.github.io/api/v1/static-site-generators/hexo.json",
      "github": "https://github.com/howtomgr/hexo"
    },
    {
      "name": "hugo",
      "title": "hugo Installation Guide",
      "description": "hugo is a free and open-source static site generator. Hugo provides fast static site generator with flexible themes",
      "difficulty_level": "intermediate",
      "estimated_setup_time": "15-30 minutes",
      "language": null,
      "stars": 0,
      "maintenance_status": "active",
      "supported_os": [
        "rhel",
        "centos",
        "rocky",
        "almalinux",
        "debian",
        "ubuntu",
        "arch",
        "alpine",
        "opensuse",
        "sles",
        "macos",
        "freebsd",
        "windows"
      ],
      "features": [
        "multi-os-support",
        "comprehensive-documentation",
        "security-hardening",
        "performance-optimization",
        "backup-restore-procedures",
        "troubleshooting-guides"
      ],
      "tags": [
        "static-site-generators",
        "containerization",
        "observability",
        "data-storage",
        "networking",
        "security",
        "data-protection"
      ],
      "site": "https://howtomgr.github.io/static-site-generators/hugo/",
      "api": "https://howtomgr.github.io/api/v1/static-site-generators/hugo.json",
      "github": "https://github.com/howtomgr/hugo"
    },
    {
      "name": "jekyll",
      "title": "jekyll Installation Guide",
      "description": "jekyll is a free and open-source static site generator. Jekyll transforms plain text into static websites and blogs",
      "difficulty_level": "intermediate",
      "estimated_setup_time": "15-30 minutes",
      "language": null,
      "stars": 0,
      "maintenance_status": "active",
      "supported_os": [
        "rhel",
        "centos",
        "rocky",
        "almalinux",
        "debian",
        "ubuntu",
        "arch",
        "alpine",
        "opensuse",
        "sles",
        "macos",
        "freebsd",
        "windows"
      ],
      "features": [
        "multi-os-support",
        "comprehensive-documentation",
        "security-hardening",
        "performance-optimization",
        "backup-restore-procedures",
        "troubleshooting-guides"
      ],
      "tags": [
        "static-site-generators",
        "containerization",
        "observability",
        "data-storage",
        "networking",
        "security",
        "data-protection"
      ],
      "site": "https://howtomgr.github.io/static-site-generators/jekyll/",
      "api": "https://howtomgr.github.io/api/v1/static-site-generators/jekyll.json",
      "github": "https://github.com/howtomgr/jekyll"
    },
    {
      "name": "metalsmith",
      "title": "metalsmith Installation Guide",
      "description": "metalsmith is a free and open-source pluggable generator. Metalsmith provides extremely simple, pluggable static site generator",
      "difficulty_level": "intermediate",
      "estimated_setup_time": "15-30 minutes",
      "language": null,
      "stars": 0,
      "maintenance_status": "active",
      "supported_os": [
        "rhel",
        "centos",
        "rocky",
        "almalinux",
        "debian",
        "ubuntu",
        "arch",
        "alpine",
        "opensuse",
        "sles",
        "macos",
        "freebsd",
        "windows"
      ],
      "features": [
        "multi-os-support",
        "comprehensive-documentation",
        "security-hardening",
        "performance-optimization",
        "backup-restore-procedures",
        "troubleshooting-guides"
      ],
      "tags": [
        "static-site-generators",
        "containerization",
        "observability",
        "data-storage",
        "networking",
        "security",
        "data-protection"
      ],
      "site": "https://howtomgr.github.io/static-site-generators/metalsmith/",
      "api": "https://howtomgr.github.io/api/v1/static-site-generators/metalsmith.json",
      "github": "https://github.com/howtomgr/metalsmith"
    },
    {
      "name": "pelican",
      "title": "pelican Installation Guide",
      "description": "pelican is a free and open-source Python static generator. Pelican provides static site generator powered by Python",
      "difficulty_level": "intermediate",
      "estimated_setup_time": "15-30 minutes",
      "language": null,
      "stars": 0,
      "maintenance_status": "active",
      "supported_os": [
        "rhel",
        "centos",
        "rocky",
        "almalinux",
        "debian",
        "ubuntu",
        "arch",
        "alpine",
        "opensuse",
        "sles",
        "macos",
        "freebsd",
        "windows"
      ],
      "features": [
        "multi-os-support",
        "comprehensive-documentation",
        "security-hardening",
        "performance-optimization",
        "backup-restore-procedures",
        "troubleshooting-guides"
      ],
      "tags": [
        "static-site-generators",
        "containerization",
        "observability",
        "data-storage",
        "networking",
        "security",
        "data-protection"
      ],
      "site": "https://howtomgr.github.io/static-site-generators/pelican/",
      "api": "https://howtomgr.github.io/api/v1/static-site-generators/pelican.json",
      "github": "https://github.com/howtomgr/pelican"
    },
    {
      "name": "vuepress",
      "title": "vuepress Installation Guide",
      "description": "vuepress is a free and open-source Vue-powered generator. VuePress provides Vue-powered static site generator",
      "difficulty_level": "intermediate",
      "estimated_setup_time": "15-30 minutes",
      "language": null,
      "stars": 0,
      "maintenance_status": "active",
      "supported_os": [
        "rhel",
        "centos",
        "rocky",
        "almalinux",
        "debian",
        "ubuntu",
        "arch",
        "alpine",
        "opensuse",
        "sles",
        "macos",
        "freebsd",
        "windows"
      ],
      "features": [
        "multi-os-support",
        "comprehensive-documentation",
        "security-hardening",
        "performance-optimization",
        "backup-restore-procedures",
        "troubleshooting-guides"
      ],
      "tags": [
        "static-site-generators",
        "containerization",
        "observability",
        "data-storage",
        "networking",
        "security",
        "data-protection"
      ],
      "site": "https://howtomgr.github.io/static-site-generators/vuepress/",
      "api": "https://howtomgr.github.io/api/v1/static-site-generators/vuepress.json",
      "github": "https://github.com/howtomgr/vuepress"
    },
    {
      "name": "wintersmith",
      "title": "wintersmith Installation Guide",
      "description": "wintersmith is a free and open-source Node.js generator. Wintersmith provides flexible, minimalistic static site generator",
      "difficulty_level": "intermediate",
      "estimated_setup_time": "15-30 minutes",
      "language": null,
      "stars": 0,
      "maintenance_status": "active",
      "supported_os": [
        "rhel",
        "centos",
        "rocky",
        "almalinux",
        "debian",
        "ubuntu",
        "arch",
        "alpine",
        "opensuse",
        "sles",
        "macos",
        "freebsd",
        "windows"
      ],
      "features": [
        "multi-os-support",
        "comprehensive-documentation",
        "security-hardening",
        "performance-optimization",
        "backup-restore-procedures",
        "troubleshooting-guides"
      ],
      "tags": [
        "static-site-generators",
        "containerization",
        "observability",
        "data-storage",
        "networking",
        "security",
        "data-protection"
      ],
      "site": "https://howtomgr.github.io/static-site-generators/wintersmith/",
      "api": "https://howtomgr.github.io/api/v1/static-site-generators/wintersmith.json",
      "github": "https://github.com/howtomgr/wintersmith"
    }
  ]
}