{
  "meta": {
    "api_version": "1.0",
    "generated_at": "2025-10-04T06:17:54.259Z",
    "spec_version": "2.0"
  },
  "tool": {
    "name": "kodi",
    "title": "kodi Installation Guide",
    "description": "kodi is a free and open-source open source media center. Kodi (formerly XBMC) provides a complete media center solution for local and network content",
    "version": "1.0.0",
    "license": "Open Source",
    "category": "media-centers",
    "subcategory": "media-centers",
    "difficulty_level": "intermediate",
    "estimated_setup_time": "15-30 minutes",
    "installation_methods": [
      "native-packages",
      "source-compilation"
    ],
    "supported_os": [
      "rhel",
      "centos",
      "rocky",
      "almalinux",
      "debian",
      "ubuntu",
      "arch",
      "alpine",
      "opensuse",
      "sles",
      "macos",
      "freebsd",
      "windows"
    ],
    "default_ports": [
      80,
      443,
      8080,
      9090
    ],
    "features": [
      "multi-os-support",
      "comprehensive-documentation",
      "security-hardening",
      "performance-optimization",
      "backup-restore-procedures",
      "troubleshooting-guides"
    ],
    "tags": [
      "media-centers",
      "containerization",
      "observability",
      "data-storage",
      "networking",
      "security",
      "data-protection"
    ],
    "maintenance_status": "active",
    "site": "https://howtomgr.github.io/media-centers/kodi/",
    "api": "https://howtomgr.github.io/api/v1/media-centers/kodi.json",
    "documentation_url": "https://howtomgr.github.io/media-centers/kodi",
    "website_url": "https://howtomgr.github.io/media-centers/kodi",
    "github_url": "https://github.com/howtomgr/kodi",
    "github_stats": {
      "stars": 0,
      "forks": 0,
      "language": null,
      "topics": [],
      "last_updated": "2025-09-16T17:24:38Z",
      "created": "2025-09-16T03:30:34Z"
    },
    "guide_info": {
      "word_count": 1279,
      "estimated_read_time": "7 min",
      "has_readme": true,
      "last_built": "2025-10-04T06:15:53.993Z"
    }
  }
}